setup.py
UsernameCCPlugin.egg-info/PKG-INFO
UsernameCCPlugin.egg-info/SOURCES.txt
UsernameCCPlugin.egg-info/dependency_links.txt
UsernameCCPlugin.egg-info/entry_points.txt
UsernameCCPlugin.egg-info/not-zip-safe
UsernameCCPlugin.egg-info/top_level.txt
usernamecc/__init__.py
usernamecc/api.py