Metadata-Version: 1.0
Name: UsernameCCPlugin
Version: 0.1.1
Summary: Make users be CCed by their username and not e-mail address.
Home-page: http://mitar.tnode.com/
Author: Mitar
Author-email: mitar.trac@tnode.com
License: AGPLv3
Keywords: trac plugin
Platform: UNKNOWN
